<?xml version="1.0" encoding="ISO-8859-1"?>
  <Model commandLine="" date="">
    <Option name="use_types" value="#off#"/>
    <Option name="imported_root_package" value="#off#"/>
    <Option name="root_package" value="#off#"/>
    <Option name="xml_basename" value="kcg_xml_filter_out.scade"/>
    <Option name="state_vector" value="#off#"/>
    <Option name="static" value="#off#"/>
    <Option name="separate_io_all" value="#off#"/>
    <Option name="no_separate_io" value="#off#"/>
    <Option name="separate_io" value="#off#"/>
    <Option name="warn_error" value="#off#"/>
    <Option name="short_circuit" value="#off#"/>
    <Option name="wrap_c_ops" value="#off#"/>
    <Option name="input_file" value="C:/Users/3771834/Desktop/tme13/Simulation/scade_model_without_unused.scade"/>
    <Option name="probes" value="#on#"/>
    <Option name="no_observe" value="#off#"/>
    <Option name="observe" value="#off#"/>
    <Option name="debug" value="#on#"/>
    <Option name="user_config" value="./user_macros.h"/>
    <Option name="input_threshold" value="#off#"/>
    <Option name="header" value="#off#"/>
    <Option name="significance_length" value="31"/>
    <Option name="name_length" value="200"/>
    <Option name="globals_prefix" value="#off#"/>
    <Option name="keep_asserts" value="#off#"/>
    <Option name="global_root_context" value="#off#"/>
    <Option name="expall" value="#off#"/>
    <Option name="noexp" value="#off#"/>
    <Option name="exp" value="#off#"/>
    <Option name="target_dir" value="C:/Users/3771834/Desktop/tme13/Simulation"/>
    <Option name="target" value="C"/>
    <Option name="root" value="tme13"/>
    <Option name="auth" value="#off#"/>
    <RootNode headerFile="tme13.h" scadeName="tme13" targetCycleFct="tme13" targetInitFct="tme13_reset" targetInitializationFct="tme13_init">
      <Input inCtx="true" scadeName="startstop" scadeType="bool" targetName="startstop" targetType="kcg_bool"/>
      <Input inCtx="true" scadeName="reset" scadeType="bool" targetName="reset" targetType="kcg_bool"/>
      <Input inCtx="true" scadeName="mode" scadeType="bool" targetName="mode" targetType="kcg_bool"/>
      <Output inCtx="true" scadeName="display" scadeType="int64^(3)" targetName="display" targetType="array_int64_3"/>
      <Signal inCtx="true" scadeName="isClock" targetName="isClock"/>
      <Local inCtx="true" scadeName="mytime" scadeType="int64^(3)" targetName="mytime" targetType="array_int64_3"/>
      <Local inCtx="true" scadeName="myclock" scadeType="int64^(3)" targetName="myclock" targetType="array_int64_3"/>
      <Local inCtx="true" scadeName="_L6" scadeType="bool" targetName="_L6" targetType="kcg_bool"/>
      <Local inCtx="true" scadeName="_L7" scadeType="int64^(4)" targetName="_L7" targetType="array_int64_4"/>
      <Local inCtx="true" scadeName="_L8" scadeType="bool" targetName="_L8" targetType="kcg_bool"/>
      <Local inCtx="true" scadeName="_L9" scadeType="int64^(4)" targetName="_L9" targetType="array_int64_4"/>
      <Local inCtx="true" scadeName="_L11" scadeType="int64^(3)" targetName="_L11" targetType="array_int64_3"/>
      <Local inCtx="true" scadeName="_L12" scadeType="int64^(4)" targetName="_L12" targetType="array_int64_4"/>
      <Automaton scadeName="chrono" targetStatesType="SSM_ST_chrono" targetTransitionsType="SSM_TR_chrono">
        <State scadeName="Pause" targetName="SSM_st_Pause_chrono">
          <Local clockVal="SSM_st_Pause_chrono" clockVar="chrono_state_act" inCtx="true" scadeName="_L3" scadeType="int64^(3)" targetName="_L3_Pause_chrono" targetType="array_int64_3"/>
          <Local clockVal="SSM_st_Pause_chrono" clockVar="chrono_state_act" inCtx="true" scadeName="_L4" scadeType="int64^(3)" targetName="_L4_Pause_chrono" targetType="array_int64_3"/>
          <InitOp instName="1"/>
          <Last/>
          <Fork priority="1">
            <Condition/>
            <Transition kind="strong" scadeDest="Run" targetName="SSM_TR_Pause_Run_1_Pause_chrono"/>
          </Fork>
          <Fork priority="2">
            <Condition/>
            <Transition kind="strong" scadeDest="Pause" targetName="SSM_TR_Pause_Pause_2_Pause_chrono"/>
          </Fork>
        </State>
        <State scadeName="Run" targetName="SSM_st_Run_chrono">
          <Local clockVal="SSM_st_Run_chrono" clockVar="chrono_state_act" inCtx="true" scadeName="_L4" scadeType="bool" targetName="_L4_Run_chrono" targetType="kcg_bool"/>
          <Local clockVal="SSM_st_Run_chrono" clockVar="chrono_state_act" inCtx="true" scadeName="_L5" scadeType="int64^(3)" targetName="_L5_Run_chrono" targetType="array_int64_3"/>
          <Local clockVal="SSM_st_Run_chrono" clockVar="chrono_state_act" inCtx="true" scadeName="_L7" scadeType="bool" targetName="_L7_Run_chrono" targetType="kcg_bool"/>
          <Local clockVal="SSM_st_Run_chrono" clockVar="chrono_state_act" inCtx="true" scadeName="_L10" scadeType="int64^(3)" targetName="_L10_Run_chrono" targetType="array_int64_3"/>
          <Local clockVal="SSM_st_Run_chrono" clockVar="chrono_state_act" inCtx="true" scadeName="_L11" scadeType="int64^(3)" targetName="_L11_Run_chrono" targetType="array_int64_3"/>
          <Iterator instName="1" iteratorKind="mapfold" scadeSize="3" targetSize="3">
            <NodeInstance clockVal="SSM_st_Run_chrono" clockVar="chrono_state_act" instName="1" refName="rawcount" scadeName="rawcount">
              <OutCtxVar clockVal="SSM_st_Run_chrono" clockVar="chrono_state_act" targetName="Context_rawcount_1"/>
            </NodeInstance>
          </Iterator>
          <Last/>
          <Fork priority="1">
            <Condition/>
            <Transition kind="strong" scadeDest="Pause" targetName="SSM_TR_Run_Pause_1_Run_chrono"/>
          </Fork>
        </State>
        <ActiveState inCtx="true" targetName="chrono_state_act"/>
        <SelectedState inCtx="true" targetName="chrono_state_sel"/>
        <NextState inCtx="true" mem="true" targetName="chrono_state_nxt"/>
        <ResetActiveState inCtx="true" mem="true" targetName="chrono_reset_act"/>
        <ResetNextState inCtx="true" mem="true" targetName="chrono_reset_nxt"/>
        <StrongTransition inCtx="true" targetName="chrono_fired_strong"/>
        <WeakTransition inCtx="true" targetName="chrono_fired"/>
      </Automaton>
      <Iterator instName="4" iteratorKind="mapfold" scadeSize="4" targetSize="4">
        <NodeInstance instName="3" refName="rawcount" scadeName="rawcount">
          <OutCtxVar targetName="Context_rawcount_3"/>
        </NodeInstance>
      </Iterator>
      <FbyOp instName="1">
        <Init inCtx="true" targetName="init" targetType="kcg_bool"/>
        <Memory inCtx="true" targetName="_L7" targetType="array_int64_4"/>
      </FbyOp>
      <Automaton scadeName="display" targetStatesType="SSM_ST_display" targetTransitionsType="SSM_TR_display">
        <State scadeName="DisplayClock" targetName="SSM_st_DisplayClock_display">
          <Local clockVal="SSM_st_DisplayClock_display" clockVar="display_state_act" inCtx="true" scadeName="_L3" scadeType="int64^(3)" targetName="_L3_DisplayClock_display" targetType="array_int64_3"/>
          <Fork priority="1">
            <Condition/>
            <Transition kind="strong" scadeDest="DisplayTime" targetName="SSM_TR_DisplayClock_DisplayTime_1_DisplayClock_display"/>
          </Fork>
        </State>
        <State scadeName="DisplayTime" targetName="SSM_st_DisplayTime_display">
          <Local clockVal="SSM_st_DisplayTime_display" clockVar="display_state_act" inCtx="true" scadeName="_L2" scadeType="int64^(3)" targetName="_L2_DisplayTime_display" targetType="array_int64_3"/>
          <Fork priority="1">
            <Condition/>
            <Transition kind="strong" scadeDest="DisplayClock" targetName="SSM_TR_DisplayTime_DisplayClock_1_DisplayTime_display"/>
          </Fork>
        </State>
        <ActiveState inCtx="true" targetName="display_state_act"/>
        <SelectedState inCtx="true" targetName="display_state_sel"/>
        <NextState inCtx="true" mem="true" targetName="display_state_nxt"/>
        <ResetActiveState inCtx="true" mem="true" targetName="display_reset_act"/>
        <ResetNextState inCtx="true" mem="true" targetName="display_reset_nxt"/>
        <StrongTransition inCtx="true" targetName="display_fired_strong"/>
        <WeakTransition inCtx="true" targetName="display_fired"/>
      </Automaton>
      <Init inCtx="true" targetName="init" targetType="kcg_bool"/>
      <Init inCtx="true" targetName="init1" targetType="kcg_bool"/>
      <Memory inCtx="true" targetName="mytime" targetType="array_int64_3"/>
      <Memory inCtx="true" targetName="_L7" targetType="array_int64_4"/>
      <Clock inCtx="true" targetName="chrono_state_act" targetType="SSM_ST_chrono"/>
      <Clock inCtx="true" targetName="display_state_act" targetType="SSM_ST_display"/>
      <OutCtxType targetName="outC_tme13"/>
      <InCtxType targetName="inC_tme13"/>
    </RootNode>
    <NoExpNode headerFile="rawcount.h" scadeName="rawcount" targetCycleFct="rawcount" targetInitFct="rawcount_reset" targetInitializationFct="rawcount_init">
      <Input scadeName="incr" scadeType="bool" targetName="incr" targetType="kcg_bool"/>
      <Input scadeName="lastcount" scadeType="int64" targetName="lastcount" targetType="kcg_int64"/>
      <Input scadeName="modulo" scadeType="int64" targetName="modulo" targetType="kcg_int64"/>
      <Output inCtx="true" scadeName="rippleclock" scadeType="bool" targetName="rippleclock" targetType="kcg_bool"/>
      <Output inCtx="true" scadeName="count" scadeType="int64" targetName="count" targetType="kcg_int64"/>
      <Local inCtx="true" scadeName="rawcount" scadeType="int64" targetName="rawcount" targetType="kcg_int64"/>
      <Local inCtx="true" scadeName="_L1" scadeType="bool" targetName="_L1" targetType="kcg_bool"/>
      <Local inCtx="true" scadeName="_L2" scadeType="int64" targetName="_L2" targetType="kcg_int64"/>
      <Local inCtx="true" scadeName="_L3" scadeType="int64" targetName="_L3" targetType="kcg_int64"/>
      <Local inCtx="true" scadeName="_L5" scadeType="int64" targetName="_L5" targetType="kcg_int64"/>
      <Local inCtx="true" scadeName="_L6" scadeType="int64" targetName="_L6" targetType="kcg_int64"/>
      <Local inCtx="true" scadeName="_L7" scadeType="bool" targetName="_L7" targetType="kcg_bool"/>
      <Local inCtx="true" scadeName="_L9" scadeType="int64" targetName="_L9" targetType="kcg_int64"/>
      <Local inCtx="true" scadeName="_L11" scadeType="int64" targetName="_L11" targetType="kcg_int64"/>
      <OutCtxType targetName="outC_rawcount"/>
    </NoExpNode>
    <ArrayType cellType="kcg_int64" size="3" targetCompFct="kcg_comp_array_int64_3" targetCopyFct="kcg_copy_array_int64_3" targetName="array_int64_3"/>
    <ArrayType cellType="kcg_int64" size="4" targetCompFct="kcg_comp_array_int64_4" targetCopyFct="kcg_copy_array_int64_4" targetName="array_int64_4"/>
    <PredefType scadeName="int8" targetName="kcg_int8"/>
    <PredefType scadeName="int16" targetName="kcg_int16"/>
    <PredefType scadeName="int32" targetName="kcg_int32"/>
    <PredefType scadeName="int64" targetName="kcg_int64"/>
    <PredefType scadeName="uint8" targetName="kcg_uint8"/>
    <PredefType scadeName="uint16" targetName="kcg_uint16"/>
    <PredefType scadeName="uint32" targetName="kcg_uint32"/>
    <PredefType scadeName="uint64" targetName="kcg_uint64"/>
    <PredefType scadeName="size" targetName="kcg_size"/>
    <PredefType scadeName="float32" targetName="kcg_float32"/>
    <PredefType scadeName="float64" targetName="kcg_float64"/>
    <PredefType scadeName="bool" targetName="kcg_bool"/>
    <PredefType scadeName="char" targetName="kcg_char"/>
  </Model>
